{"remove":{"path":"part-00001-9cb3bff8-b581-4380-b311-1fead3490a99-c000.snappy.parquet","dataChange":true,"deletionTimestamp":1771611170397,"extendedFileMetadata":true,"partitionValues":{},"size":3224}}
{"add":{"path":"part-00001-c632deed-874c-4c7a-b3be-44a36934885a-c000.snappy.parquet","partitionValues":{},"size":3224,"modificationTime":1771611170427,"dataChange":true,"stats":"{\"numRecords\":30,\"minValues\":{\"event_id\":\"ev_001\",\"event_time\":\"2026-02-20T14:01:00Z\",\"channel\":\"marketplace\",\"gmv\":40.0,\"qty\":1,\"seller_id\":\"seller_a\",\"sku\":\"sku_1\",\"price\":40.0},\"maxValues\":{\"event_id\":\"ev_030\",\"seller_id\":\"seller_c\",\"price\":100.0,\"sku\":\"sku_5\",\"qty\":4,\"event_time\":\"2026-02-20T14:30:00Z\",\"channel\":\"web\",\"gmv\":400.0},\"nullCount\":{\"event_id\":0,\"event_time\":0,\"qty\":0,\"price\":0,\"channel\":0,\"sku\":0,\"seller_id\":0,\"gmv\":0}}","tags":null,"deletionVector":null,"baseRowId":null,"defaultRowCommitVersion":null,"clusteringProvider":null}}
{"commitInfo":{"timestamp":1771611170428,"operation":"WRITE","operationParameters":{"mode":"Overwrite"},"clientVersion":"delta-rs.py-0.25.5","operationMetrics":{"execution_time_ms":34,"num_added_files":1,"num_added_rows":30,"num_partitions":0,"num_removed_files":1}}}